{
  "version": "0.0.1",
  "lastUpdated": "2026-01-01",
  "games": [
    {
      "id": "spaced",
      "title": "Spaced",
      "developer": "BOPware",
      "version": "0.1.0",
      "genre": "Arcade",
      "tags": ["arcade", "space", "action"],
      "description": "Lost signals. Drifting debris. Something is out there between the stars — and it found you first.",
      "shortDesc": "Deep space survival arcade",
      "thumbnail": "assets/images/thumbs/spaced.png",
      "thumbnailPlaceholderColor": "#0a1628",
      "path": "apps/spaced/index.html",
      "featured": true,
      "isNew": true,
      "dateAdded": "2026-01-01",
      "lastPlayed": null,
      "playCount": 0,
      "unlocked": true,
      "hidden": false,
      "pinned": false,
      "row": 0
    },
    {
      "id": "grablab",
      "title": "Grab Lab",
      "developer": "BOPware",
      "version": "0.1.0",
      "genre": "Puzzle",
      "tags": ["puzzle", "physics", "lab"],
      "description": "The lab equipment isn't supposed to move on its own. Grab what you can before the experiment ends you.",
      "shortDesc": "Physics-based grab puzzle",
      "thumbnail": "assets/images/thumbs/grablab.png",
      "thumbnailPlaceholderColor": "#0d2613",
      "path": "apps/grablab/index.html",
      "featured": false,
      "isNew": true,
      "dateAdded": "2026-01-01",
      "lastPlayed": null,
      "playCount": 0,
      "unlocked": true,
      "hidden": false,
      "pinned": false,
      "row": 0
    },
    {
      "id": "mutantmusician",
      "title": "Mutant Musician Lab",
      "developer": "BOPware",
      "version": "0.1.0",
      "genre": "Creative",
      "tags": ["music", "creative", "weird"],
      "description": "Part synthesizer. Part organism. Fully unclassified. Create sounds that have no right to exist.",
      "shortDesc": "Mutant music creation tool",
      "thumbnail": "assets/images/thumbs/mutantmusician.png",
      "thumbnailPlaceholderColor": "#1a0a2e",
      "path": "apps/mutantmusician/index.html",
      "featured": false,
      "isNew": true,
      "dateAdded": "2026-01-01",
      "lastPlayed": null,
      "playCount": 0,
      "unlocked": true,
      "hidden": false,
      "pinned": false,
      "row": 1
    },
    {
      "id": "gamebuddy",
      "title": "Game Buddy",
      "developer": "BOPware",
      "version": "0.1.0",
      "genre": "Utility",
      "tags": ["utility", "companion", "tools"],
      "description": "Your personal game companion. Tracks, hints, maps, and weird data you didn't know you needed.",
      "shortDesc": "Game companion utility",
      "thumbnail": "assets/images/thumbs/gamebuddy.png",
      "thumbnailPlaceholderColor": "#1a1200",
      "path": "apps/gamebuddy/index.html",
      "featured": false,
      "isNew": false,
      "dateAdded": "2026-01-01",
      "lastPlayed": null,
      "playCount": 0,
      "unlocked": true,
      "hidden": false,
      "pinned": false,
      "row": 1
    },
    {
      "id": "surviveall",
      "title": "SurviveAll",
      "developer": "BOPware",
      "version": "0.1.0",
      "genre": "Survival",
      "tags": ["survival", "roguelike", "action"],
      "description": "Everything is trying to end you. Survive anyway. No instructions included. You won't need them.",
      "shortDesc": "Survival roguelike",
      "thumbnail": "assets/images/thumbs/surviveall.png",
      "thumbnailPlaceholderColor": "#1a0000",
      "path": "apps/surviveall/index.html",
      "featured": false,
      "isNew": false,
      "dateAdded": "2026-01-01",
      "lastPlayed": null,
      "playCount": 0,
      "unlocked": true,
      "hidden": false,
      "pinned": false,
      "row": 1
    },
    {
      "id": "placeholder_6",
      "title": "CLASSIFIED",
      "developer": "BOPware",
      "version": "???",
      "genre": "Unknown",
      "tags": ["locked", "mystery"],
      "description": "Signal detected. Unable to decode. Check back after next system update.",
      "shortDesc": "???.???",
      "thumbnail": "assets/images/thumbs/classified.png",
      "thumbnailPlaceholderColor": "#0a0a0a",
      "path": null,
      "featured": false,
      "isNew": false,
      "dateAdded": "2026-01-01",
      "lastPlayed": null,
      "playCount": 0,
      "unlocked": false,
      "hidden": false,
      "pinned": false,
      "row": 2
    }
  ],
  "systemApps": [
    {
      "id": "bopmedia",
      "title": "BOP Media",
      "icon": "🎵",
      "iconFile": "assets/images/icons/bopmedia.svg",
      "description": "Audio & video player for the BOPware Deck",
      "path": "apps/system/bopmedia.html",
      "pinned": true,
      "order": 0
    },
    {
      "id": "notestick",
      "title": "NoteStick",
      "icon": "📝",
      "iconFile": "assets/images/icons/notestick.svg",
      "description": "Sticky notes you can place anywhere on the deck screen",
      "path": "apps/system/notestick.html",
      "pinned": true,
      "order": 1
    },
    {
      "id": "messages",
      "title": "Transmissions",
      "icon": "📡",
      "iconFile": "assets/images/icons/messages.svg",
      "description": "System messages, boot logs, and deep-space transmissions",
      "path": "apps/system/messages.html",
      "pinned": true,
      "order": 2
    },
    {
      "id": "settings",
      "title": "Settings",
      "icon": "⚙️",
      "iconFile": "assets/images/icons/settings.svg",
      "description": "BOPware Deck system configuration",
      "path": "apps/system/settings.html",
      "pinned": true,
      "order": 3
    }
  ],
  "rows": [
    { "id": 0, "label": "Featured & New", "filter": "featured" },
    { "id": 1, "label": "Your Library", "filter": "all" },
    { "id": 2, "label": "Incoming Signal", "filter": "locked" }
  ]
}
